[{"distance": 226.8908710591212, "event_location": {"type": "Point", "coordinates": [-90.478849, 38.644193]}, "event": "2014inwl", "team_location": {"type": "Point", "coordinates": [-86.90807, 40.42587]}, "team": 1329}, {"distance": 60.125132736422145, "event_location": {"type": "Point", "coordinates": [-86.062297, 39.844487]}, "event": "2014inwl", "team_location": {"type": "Point", "coordinates": [-86.90807, 40.42587]}, "team": 4545}, {"distance": 64.90880956329981, "event_location": {"type": "Point", "coordinates": [-85.996975, 39.796814]}, "event": "2014inwl", "team_location": {"type": "Point", "coordinates": [-86.90807, 40.42587]}, "team": 829}, {"distance": 51.89086704261774, "event_location": {"type": "Point", "coordinates": [-86.11966, 39.978457]}, "event": "2014inwl", "team_location": {"type": "Point", "coordinates": [-86.90807, 40.42587]}, "team": 868}, {"distance": 146.91335073876925, "event_location": {"type": "Point", "coordinates": [-89.53811, 39.752086]}, "event": "2014inwl", "team_location": {"type": "Point", "coordinates": [-86.90807, 40.42587]}, "team": 2909}, {"distance": 0.7294327865751573, "event_location": {"type": "Point", "coordinates": [-86.910779, 40.436237]}, "event": "2014inwl", "team_location": {"type": "Point", "coordinates": [-86.90807, 40.42587]}, "team": 461}, {"distance": 84.54294484378761, "event_location": {"type": "Point", "coordinates": [-85.540624, 39.794108]}, "event": "2014inwl", "team_location": {"type": "Point", "coordinates": [-86.90807, 40.42587]}, "team": 3947}, {"distance": 485.87948641996013, "event_location": {"type": "Point", "coordinates": [-80.004909, 35.953806]}, "event": "2014inwl", "team_location": {"type": "Point", "coordinates": [-86.90807, 40.42587]}, "team": 2655}, {"distance": 1959.9779856313141, "event_location": {"type": "Point", "coordinates": [-66.111, 18.35745]}, "event": "2014inwl", "team_location": {"type": "Point", "coordinates": [-86.90807, 40.42587]}, "team": 5010}, {"distance": 124.7902002467614, "event_location": {"type": "Point", "coordinates": [-86.314553, 42.17793]}, "event": "2014inwl", "team_location": {"type": "Point", "coordinates": [-86.90807, 40.42587]}, "team": 2959}, {"distance": 80.70928753963825, "event_location": {"type": "Point", "coordinates": [-86.161566, 39.407002]}, "event": "2014inwl", "team_location": {"type": "Point", "coordinates": [-86.90807, 40.42587]}, "team": 3180}, {"distance": 40.167135132080354, "event_location": {"type": "Point", "coordinates": [-86.14817, 40.469001]}, "event": "2014inwl", "team_location": {"type": "Point", "coordinates": [-86.90807, 40.42587]}, "team": 45}, {"distance": 91.5923643746816, "event_location": {"type": "Point", "coordinates": [-86.244392, 41.654394]}, "event": "2014inwl", "team_location": {"type": "Point", "coordinates": [-86.90807, 40.42587]}, "team": 3865}, {"distance": 66.02457074329193, "event_location": {"type": "Point", "coordinates": [-86.143028, 39.670824]}, "event": "2014inwl", "team_location": {"type": "Point", "coordinates": [-86.90807, 40.42587]}, "team": 1529}, {"distance": 91.55354047324516, "event_location": {"type": "Point", "coordinates": [-86.31415, 41.674116]}, "event": "2014inwl", "team_location": {"type": "Point", "coordinates": [-86.90807, 40.42587]}, "team": 4791}, {"distance": 99.3681777517405, "event_location": {"type": "Point", "coordinates": [-85.023515, 40.43044]}, "event": "2014inwl", "team_location": {"type": "Point", "coordinates": [-86.90807, 40.42587]}, "team": 3301}, {"distance": 5.169226448056389, "event_location": {"type": "Point", "coordinates": [-86.903293, 40.351041]}, "event": "2014inwl", "team_location": {"type": "Point", "coordinates": [-86.90807, 40.42587]}, "team": 4272}, {"distance": 35.08517618112711, "event_location": {"type": "Point", "coordinates": [-86.24282, 40.437762]}, "event": "2014inwl", "team_location": {"type": "Point", "coordinates": [-86.90807, 40.42587]}, "team": 292}, {"distance": 152.31772916805585, "event_location": {"type": "Point", "coordinates": [-85.15679, 38.683077]}, "event": "2014inwl", "team_location": {"type": "Point", "coordinates": [-86.90807, 40.42587]}, "team": 3272}, {"distance": 107.32935388441504, "event_location": {"type": "Point", "coordinates": [-88.943109, 40.481095]}, "event": "2014inwl", "team_location": {"type": "Point", "coordinates": [-86.90807, 40.42587]}, "team": 4213}, {"distance": 144.5657848098415, "event_location": {"type": "Point", "coordinates": [-89.63475, 40.679603]}, "event": "2014inwl", "team_location": {"type": "Point", "coordinates": [-86.90807, 40.42587]}, "team": 1756}, {"distance": 5.084423167090277, "event_location": {"type": "Point", "coordinates": [-86.914977, 40.499369]}, "event": "2014inwl", "team_location": {"type": "Point", "coordinates": [-86.90807, 40.42587]}, "team": 1747}, {"distance": 58.37035212143873, "event_location": {"type": "Point", "coordinates": [-86.161321, 39.803751]}, "event": "2014inwl", "team_location": {"type": "Point", "coordinates": [-86.90807, 40.42587]}, "team": 4211}, {"distance": 69.70928086029949, "event_location": {"type": "Point", "coordinates": [-86.196938, 39.576303]}, "event": "2014inwl", "team_location": {"type": "Point", "coordinates": [-86.90807, 40.42587]}, "team": 1741}, {"distance": 45.00558268734262, "event_location": {"type": "Point", "coordinates": [-86.054577, 40.434244]}, "event": "2014inwl", "team_location": {"type": "Point", "coordinates": [-86.90807, 40.42587]}, "team": 1760}, {"distance": 62.0873882902713, "event_location": {"type": "Point", "coordinates": [-86.140925, 39.745722]}, "event": "2014inwl", "team_location": {"type": "Point", "coordinates": [-86.90807, 40.42587]}, "team": 4234}, {"distance": 84.12867181453285, "event_location": {"type": "Point", "coordinates": [-87.338619, 41.6006]}, "event": "2014inwl", "team_location": {"type": "Point", "coordinates": [-86.90807, 40.42587]}, "team": 4846}, {"distance": 55.075337736237856, "event_location": {"type": "Point", "coordinates": [-86.28947, 39.784326]}, "event": "2014inwl", "team_location": {"type": "Point", "coordinates": [-86.90807, 40.42587]}, "team": 4580}, {"distance": 96.00064823494945, "event_location": {"type": "Point", "coordinates": [-86.109627, 41.678916]}, "event": "2014inwl", "team_location": {"type": "Point", "coordinates": [-86.90807, 40.42587]}, "team": 135}, {"distance": 99.30989721316337, "event_location": {"type": "Point", "coordinates": [-86.014044, 41.69602]}, "event": "2014inwl", "team_location": {"type": "Point", "coordinates": [-86.90807, 40.42587]}, "team": 2867}, {"distance": 83.8870781108703, "event_location": {"type": "Point", "coordinates": [-87.505417, 41.554132]}, "event": "2014inwl", "team_location": {"type": "Point", "coordinates": [-86.90807, 40.42587]}, "team": 3147}, {"distance": 49.59463411588683, "event_location": {"type": "Point", "coordinates": [-86.3871, 39.82857]}, "event": "2014inwl", "team_location": {"type": "Point", "coordinates": [-86.90807, 40.42587]}, "team": 3176}, {"distance": 50.15075818538419, "event_location": {"type": "Point", "coordinates": [-86.540505, 39.756051]}, "event": "2014inwl", "team_location": {"type": "Point", "coordinates": [-86.90807, 40.42587]}, "team": 4485}, {"distance": 50.97545587403206, "event_location": {"type": "Point", "coordinates": [-86.258731, 39.88034]}, "event": "2014inwl", "team_location": {"type": "Point", "coordinates": [-86.90807, 40.42587]}, "team": 1018}, {"distance": 2.404807044016459, "event_location": {"type": "Point", "coordinates": [-86.875059, 40.401827]}, "event": "2014inwl", "team_location": {"type": "Point", "coordinates": [-86.90807, 40.42587]}, "team": 1646}, {"distance": 66.96813916676838, "event_location": {"type": "Point", "coordinates": [-85.843249, 39.901735]}, "event": "2014inwl", "team_location": {"type": "Point", "coordinates": [-86.90807, 40.42587]}, "team": 4927}, {"distance": 321.34589438058117, "event_location": {"type": "Point", "coordinates": [-81.942869, 37.826938]}, "event": "2014inwl", "team_location": {"type": "Point", "coordinates": [-86.90807, 40.42587]}, "team": 337}, {"distance": 37.622390306911356, "event_location": {"type": "Point", "coordinates": [-86.332939, 40.749986]}, "event": "2014inwl", "team_location": {"type": "Point", "coordinates": [-86.90807, 40.42587]}, "team": 4824}, {"distance": 57.16864106960317, "event_location": {"type": "Point", "coordinates": [-86.395766, 39.696743]}, "event": "2014inwl", "team_location": {"type": "Point", "coordinates": [-86.90807, 40.42587]}, "team": 3487}, {"distance": 73.6621752408583, "event_location": {"type": "Point", "coordinates": [-85.511264, 40.453101]}, "event": "2014inwl", "team_location": {"type": "Point", "coordinates": [-86.90807, 40.42587]}, "team": 1720}]