[{"distance": 174.29329960482409, "event_location": {"type": "Point", "coordinates": [-113.550982, 53.549565]}, "event": "2014abca", "team_location": {"type": "Point", "coordinates": [-114.08529, 51.05011]}, "team": 5064}, {"distance": 1441.6699876941389, "event_location": {"type": "Point", "coordinates": [-85.77006, 42.879636]}, "event": "2014abca", "team_location": {"type": "Point", "coordinates": [-114.08529, 51.05011]}, "team": 244}, {"distance": 15.542057317312539, "event_location": {"type": "Point", "coordinates": [-114.016657, 51.270758]}, "event": "2014abca", "team_location": {"type": "Point", "coordinates": [-114.08529, 51.05011]}, "team": 5185}, {"distance": 3.088986938012371, "event_location": {"type": "Point", "coordinates": [-114.111902, 51.008695]}, "event": "2014abca", "team_location": {"type": "Point", "coordinates": [-114.08529, 51.05011]}, "team": 4751}, {"distance": 1441.6699876941389, "event_location": {"type": "Point", "coordinates": [-85.77006, 42.879636]}, "event": "2014abca", "team_location": {"type": "Point", "coordinates": [-114.08529, 51.05011]}, "team": 216}, {"distance": 260.1028267049626, "event_location": {"type": "Point", "coordinates": [-116.777467, 47.721178]}, "event": "2014abca", "team_location": {"type": "Point", "coordinates": [-114.08529, 51.05011]}, "team": 3145}, {"distance": 1677.4104825353595, "event_location": {"type": "Point", "coordinates": [-79.517778, 43.835244]}, "event": "2014abca", "team_location": {"type": "Point", "coordinates": [-114.08529, 51.05011]}, "team": 4497}, {"distance": 4.271313321052344, "event_location": {"type": "Point", "coordinates": [-114.141233, 51.100863]}, "event": "2014abca", "team_location": {"type": "Point", "coordinates": [-114.08529, 51.05011]}, "team": 4719}, {"distance": 3.088986938012371, "event_location": {"type": "Point", "coordinates": [-114.111902, 51.008695]}, "event": "2014abca", "team_location": {"type": "Point", "coordinates": [-114.08529, 51.05011]}, "team": 4604}, {"distance": 6.78636438208221, "event_location": {"type": "Point", "coordinates": [-113.954, 51.103]}, "event": "2014abca", "team_location": {"type": "Point", "coordinates": [-114.08529, 51.05011]}, "team": 4634}, {"distance": 4.481843238701669, "event_location": {"type": "Point", "coordinates": [-114.139609, 50.995065]}, "event": "2014abca", "team_location": {"type": "Point", "coordinates": [-114.08529, 51.05011]}, "team": 5228}, {"distance": 167.90644295389762, "event_location": {"type": "Point", "coordinates": [-113.580327, 53.458727]}, "event": "2014abca", "team_location": {"type": "Point", "coordinates": [-114.08529, 51.05011]}, "team": 5140}, {"distance": 256.52237627337024, "event_location": {"type": "Point", "coordinates": [-116.879575, 47.8156]}, "event": "2014abca", "team_location": {"type": "Point", "coordinates": [-114.08529, 51.05011]}, "team": 3513}, {"distance": 407.4940769092936, "event_location": {"type": "Point", "coordinates": [-111.433189, 56.731247]}, "event": "2014abca", "team_location": {"type": "Point", "coordinates": [-114.08529, 51.05011]}, "team": 4625}, {"distance": 114.68019631461384, "event_location": {"type": "Point", "coordinates": [-113.30541, 49.467998]}, "event": "2014abca", "team_location": {"type": "Point", "coordinates": [-114.08529, 51.05011]}, "team": 5118}, {"distance": 1646.960019668148, "event_location": {"type": "Point", "coordinates": [-79.748399, 44.446229]}, "event": "2014abca", "team_location": {"type": "Point", "coordinates": [-114.08529, 51.05011]}, "team": 2013}, {"distance": 290.2078266389366, "event_location": {"type": "Point", "coordinates": [-114.057761, 46.85044]}, "event": "2014abca", "team_location": {"type": "Point", "coordinates": [-114.08529, 51.05011]}, "team": 3216}, {"distance": 102.08967320576129, "event_location": {"type": "Point", "coordinates": [-111.885026, 50.562567]}, "event": "2014abca", "team_location": {"type": "Point", "coordinates": [-114.08529, 51.05011]}, "team": 5292}, {"distance": 7.3393238898488375, "event_location": {"type": "Point", "coordinates": [-114.195063, 51.13069]}, "event": "2014abca", "team_location": {"type": "Point", "coordinates": [-114.08529, 51.05011]}, "team": 5117}, {"distance": 4.623215942930825, "event_location": {"type": "Point", "coordinates": [-114.18905, 51.036171]}, "event": "2014abca", "team_location": {"type": "Point", "coordinates": [-114.08529, 51.05011]}, "team": 4627}, {"distance": 1683.8722366460172, "event_location": {"type": "Point", "coordinates": [-79.655737, 43.473116]}, "event": "2014abca", "team_location": {"type": "Point", "coordinates": [-114.08529, 51.05011]}, "team": 1334}, {"distance": 169.70241489692572, "event_location": {"type": "Point", "coordinates": [-113.516884, 53.479654]}, "event": "2014abca", "team_location": {"type": "Point", "coordinates": [-114.08529, 51.05011]}, "team": 5184}, {"distance": 5.610691885983711, "event_location": {"type": "Point", "coordinates": [-113.960838, 51.071016]}, "event": "2014abca", "team_location": {"type": "Point", "coordinates": [-114.08529, 51.05011]}, "team": 4733}, {"distance": 2.6248408607246976, "event_location": {"type": "Point", "coordinates": [-114.068496, 51.086577]}, "event": "2014abca", "team_location": {"type": "Point", "coordinates": [-114.08529, 51.05011]}, "team": 5296}, {"distance": 2.99348740023772, "event_location": {"type": "Point", "coordinates": [-114.120504, 51.012932]}, "event": "2014abca", "team_location": {"type": "Point", "coordinates": [-114.08529, 51.05011]}, "team": 4334}, {"distance": 16.890121020905454, "event_location": {"type": "Point", "coordinates": [-114.006295, 51.289339]}, "event": "2014abca", "team_location": {"type": "Point", "coordinates": [-114.08529, 51.05011]}, "team": 5015}, {"distance": 5.152943329429888, "event_location": {"type": "Point", "coordinates": [-114.077443, 50.975731]}, "event": "2014abca", "team_location": {"type": "Point", "coordinates": [-114.08529, 51.05011]}, "team": 1482}, {"distance": 320.2206607499433, "event_location": {"type": "Point", "coordinates": [-112.04952, 46.614636]}, "event": "2014abca", "team_location": {"type": "Point", "coordinates": [-114.08529, 51.05011]}, "team": 1695}, {"distance": 3.5063953045999408, "event_location": {"type": "Point", "coordinates": [-114.159007, 51.029788]}, "event": "2014abca", "team_location": {"type": "Point", "coordinates": [-114.08529, 51.05011]}, "team": 5078}, {"distance": 7.4894026181971185, "event_location": {"type": "Point", "coordinates": [-114.066117, 51.157777]}, "event": "2014abca", "team_location": {"type": "Point", "coordinates": [-114.08529, 51.05011]}, "team": 4591}, {"distance": 1441.6699876941389, "event_location": {"type": "Point", "coordinates": [-85.77006, 42.879636]}, "event": "2014abca", "team_location": {"type": "Point", "coordinates": [-114.08529, 51.05011]}, "team": 288}, {"distance": 192.05637873276024, "event_location": {"type": "Point", "coordinates": [-116.327126, 48.678632]}, "event": "2014abca", "team_location": {"type": "Point", "coordinates": [-114.08529, 51.05011]}, "team": 2130}, {"distance": 4.445655976598614, "event_location": {"type": "Point", "coordinates": [-114.186504, 51.058274]}, "event": "2014abca", "team_location": {"type": "Point", "coordinates": [-114.08529, 51.05011]}, "team": 5116}, {"distance": 10.60809268667742, "event_location": {"type": "Point", "coordinates": [-114.063325, 50.897278]}, "event": "2014abca", "team_location": {"type": "Point", "coordinates": [-114.08529, 51.05011]}, "team": 4633}, {"distance": 2334.352346389887, "event_location": {"type": "Point", "coordinates": [-99.225, 19.308333]}, "event": "2014abca", "team_location": {"type": "Point", "coordinates": [-114.08529, 51.05011]}, "team": 4010}, {"distance": 1785.6097495992865, "event_location": {"type": "Point", "coordinates": [-75.924976, 45.322352]}, "event": "2014abca", "team_location": {"type": "Point", "coordinates": [-114.08529, 51.05011]}, "team": 2994}]