[{"distance": 50.88979558809153, "event_location": {"type": "Point", "coordinates": [-72.540686, 42.000963]}, "event": "2014ctgro", "team_location": {"type": "Point", "coordinates": [-72.07841, 41.3501]}, "team": 175}, {"distance": 30.855315858166236, "event_location": {"type": "Point", "coordinates": [-72.620637, 41.532949]}, "event": "2014ctgro", "team_location": {"type": "Point", "coordinates": [-72.07841, 41.3501]}, "team": 4557}, {"distance": 1.0361201148396548, "event_location": {"type": "Point", "coordinates": [-72.096469, 41.356445]}, "event": "2014ctgro", "team_location": {"type": "Point", "coordinates": [-72.07841, 41.3501]}, "team": 3719}, {"distance": 57.76115168794943, "event_location": {"type": "Point", "coordinates": [-73.167555, 41.190829]}, "event": "2014ctgro", "team_location": {"type": "Point", "coordinates": [-72.07841, 41.3501]}, "team": 3634}, {"distance": 32.84992601038393, "event_location": {"type": "Point", "coordinates": [-72.249523, 41.808431]}, "event": "2014ctgro", "team_location": {"type": "Point", "coordinates": [-72.07841, 41.3501]}, "team": 3555}, {"distance": 85.0765413796665, "event_location": {"type": "Point", "coordinates": [-71.092339, 42.338009]}, "event": "2014ctgro", "team_location": {"type": "Point", "coordinates": [-72.07841, 41.3501]}, "team": 125}, {"distance": 39.649064318227374, "event_location": {"type": "Point", "coordinates": [-72.75222, 41.62096]}, "event": "2014ctgro", "team_location": {"type": "Point", "coordinates": [-72.07841, 41.3501]}, "team": 155}, {"distance": 40.240398768393405, "event_location": {"type": "Point", "coordinates": [-71.714999, 41.865461]}, "event": "2014ctgro", "team_location": {"type": "Point", "coordinates": [-72.07841, 41.3501]}, "team": 5112}, {"distance": 42.694278254755496, "event_location": {"type": "Point", "coordinates": [-71.287138, 41.517875]}, "event": "2014ctgro", "team_location": {"type": "Point", "coordinates": [-72.07841, 41.3501]}, "team": 121}, {"distance": 50.44179903667498, "event_location": {"type": "Point", "coordinates": [-72.862315, 41.783281]}, "event": "2014ctgro", "team_location": {"type": "Point", "coordinates": [-72.07841, 41.3501]}, "team": 1124}, {"distance": 49.344249694439775, "event_location": {"type": "Point", "coordinates": [-72.867637, 41.749784]}, "event": "2014ctgro", "team_location": {"type": "Point", "coordinates": [-72.07841, 41.3501]}, "team": 178}, {"distance": 31.795141105221568, "event_location": {"type": "Point", "coordinates": [-72.68396, 41.287941]}, "event": "2014ctgro", "team_location": {"type": "Point", "coordinates": [-72.07841, 41.3501]}, "team": 2067}, {"distance": 59.46207996985366, "event_location": {"type": "Point", "coordinates": [-73.189765, 41.55833]}, "event": "2014ctgro", "team_location": {"type": "Point", "coordinates": [-72.07841, 41.3501]}, "team": 2836}, {"distance": 44.940405267776306, "event_location": {"type": "Point", "coordinates": [-72.94034, 41.305882]}, "event": "2014ctgro", "team_location": {"type": "Point", "coordinates": [-72.07841, 41.3501]}, "team": 558}, {"distance": 36.07083385938112, "event_location": {"type": "Point", "coordinates": [-72.593365, 41.701435]}, "event": "2014ctgro", "team_location": {"type": "Point", "coordinates": [-72.07841, 41.3501]}, "team": 2170}, {"distance": 45.1221261808436, "event_location": {"type": "Point", "coordinates": [-72.744063, 41.771452]}, "event": "2014ctgro", "team_location": {"type": "Point", "coordinates": [-72.07841, 41.3501]}, "team": 1991}, {"distance": 39.47399958734782, "event_location": {"type": "Point", "coordinates": [-71.48912, 41.71217]}, "event": "2014ctgro", "team_location": {"type": "Point", "coordinates": [-72.07841, 41.3501]}, "team": 78}, {"distance": 19.38265110613914, "event_location": {"type": "Point", "coordinates": [-72.302838, 41.574562]}, "event": "2014ctgro", "team_location": {"type": "Point", "coordinates": [-72.07841, 41.3501]}, "team": 1699}, {"distance": 57.31154349663497, "event_location": {"type": "Point", "coordinates": [-73.163302, 41.501568]}, "event": "2014ctgro", "team_location": {"type": "Point", "coordinates": [-72.07841, 41.3501]}, "team": 2064}, {"distance": 44.28015251328472, "event_location": {"type": "Point", "coordinates": [-72.805423, 41.686459]}, "event": "2014ctgro", "team_location": {"type": "Point", "coordinates": [-72.07841, 41.3501]}, "team": 3718}, {"distance": 33.30995502095897, "event_location": {"type": "Point", "coordinates": [-72.674475, 41.528403]}, "event": "2014ctgro", "team_location": {"type": "Point", "coordinates": [-72.07841, 41.3501]}, "team": 3654}, {"distance": 68.76443897669662, "event_location": {"type": "Point", "coordinates": [-73.391043, 41.478495]}, "event": "2014ctgro", "team_location": {"type": "Point", "coordinates": [-72.07841, 41.3501]}, "team": 1099}, {"distance": 38.24863415313589, "event_location": {"type": "Point", "coordinates": [-72.774374, 41.53155]}, "event": "2014ctgro", "team_location": {"type": "Point", "coordinates": [-72.07841, 41.3501]}, "team": 228}, {"distance": 63.52290976853221, "event_location": {"type": "Point", "coordinates": [-73.047651, 41.914435]}, "event": "2014ctgro", "team_location": {"type": "Point", "coordinates": [-72.07841, 41.3501]}, "team": 4055}, {"distance": 43.96495502309977, "event_location": {"type": "Point", "coordinates": [-72.923833, 41.346652]}, "event": "2014ctgro", "team_location": {"type": "Point", "coordinates": [-72.07841, 41.3501]}, "team": 5142}, {"distance": 54.17241648913551, "event_location": {"type": "Point", "coordinates": [-73.119102, 41.31909]}, "event": "2014ctgro", "team_location": {"type": "Point", "coordinates": [-72.07841, 41.3501]}, "team": 230}, {"distance": 44.555758322009545, "event_location": {"type": "Point", "coordinates": [-72.859974, 41.617358]}, "event": "2014ctgro", "team_location": {"type": "Point", "coordinates": [-72.07841, 41.3501]}, "team": 195}, {"distance": 55.73308961240039, "event_location": {"type": "Point", "coordinates": [-73.102173, 41.593686]}, "event": "2014ctgro", "team_location": {"type": "Point", "coordinates": [-72.07841, 41.3501]}, "team": 237}, {"distance": 46.421888017149996, "event_location": {"type": "Point", "coordinates": [-72.751373, 41.794047]}, "event": "2014ctgro", "team_location": {"type": "Point", "coordinates": [-72.07841, 41.3501]}, "team": 3182}, {"distance": 3.560072824931714, "event_location": {"type": "Point", "coordinates": [-72.010642, 41.342799]}, "event": "2014ctgro", "team_location": {"type": "Point", "coordinates": [-72.07841, 41.3501]}, "team": 2168}, {"distance": 13.146422292223978, "event_location": {"type": "Point", "coordinates": [-72.327783, 41.319071]}, "event": "2014ctgro", "team_location": {"type": "Point", "coordinates": [-72.07841, 41.3501]}, "team": 236}, {"distance": 42.35503341557247, "event_location": {"type": "Point", "coordinates": [-72.673953, 41.770326]}, "event": "2014ctgro", "team_location": {"type": "Point", "coordinates": [-72.07841, 41.3501]}, "team": 181}, {"distance": 45.32878925668526, "event_location": {"type": "Point", "coordinates": [-72.655662, 41.843709]}, "event": "2014ctgro", "team_location": {"type": "Point", "coordinates": [-72.07841, 41.3501]}, "team": 571}]